example/__init__.py
example/main.py
ghrc_process/__init__.py
ghrc_process/cli.py
ghrc_process/handlers.py
ghrc_process/helpers.py
ghrc_process/loggers.py
ghrc_process/process.py
ghrc_process/s3.py
ghrc_process/version.py
ghrc_process-0.9.2.dist-info/LICENSE
ghrc_process-0.9.2.dist-info/METADATA
ghrc_process-0.9.2.dist-info/WHEEL
ghrc_process-0.9.2.dist-info/top_level.txt
ghrc_process-0.9.2.dist-info/RECORD
