Metadata-Version: 2.1
Name: ghrc-process
Version: 0.9.2
Summary: Library for creating Cumulus Process tasks in Python
Home-page: https://github.com/nasa-cumulus/cumulus-process-py
Author: Matthew Hanson (matthewhanson), Alireza J (scisco)
Author-email: UNKNOWN
License: Apache 2.0
Platform: UNKNOWN
Classifier: Topic :: Software Development :: Libraries
Classifier: Topic :: Scientific/Engineering
Classifier: Intended Audience :: Developers
Classifier: Intended Audience :: Science/Research
Classifier: License :: OSI Approved :: Apache Software License
Classifier: Programming Language :: Python :: 2.7
Classifier: Programming Language :: Python :: 3.5
Classifier: Programming Language :: Python :: 3.6
Requires-Dist: boto3 (~=1.12.47)
Requires-Dist: six (~=1.12.0)
Requires-Dist: python-json-logger (~=0.1)
Requires-Dist: dicttoxml (~=1.7)
Requires-Dist: cumulus-message-adapter-python (~=1.2.0)
Requires-Dist: apscheduler (~=3.6.1)
Requires-Dist: SQLAlchemy (~=1.3.8)
